dtfuncs/__init__.py
dtfuncs/round_down.py
dtfuncs-0.0.1.dist-info/LICENSE
dtfuncs-0.0.1.dist-info/METADATA
dtfuncs-0.0.1.dist-info/WHEEL
dtfuncs-0.0.1.dist-info/top_level.txt
dtfuncs-0.0.1.dist-info/RECORD
