Metadata-Version: 2.1
Name: dtfuncs
Version: 0.0.1
Summary: Useful functions to work with date and time
Home-page: https://github.com/p0m1d0rka/dtfuncs
Author: Vladimir Elizarov
Author-email: vladimirelizarov89@gmail.com
License: UNKNOWN
Platform: UNKNOWN
Classifier: Programming Language :: Python :: 3
Classifier: License :: OSI Approved :: MIT License
Classifier: Operating System :: OS Independent
Requires-Python: >=3.6
